shift_reg.v
module shift_reg (
    input clk,              // Clock signal
    input rst,              // Reset signal (active high)
    input load,             // Parallel load signal (active high)
    input [3:0] data_in,    // 4-bit parallel data input
    input shift_dir,        // Shift direction (0 = right, 1 = left)
    input serial_in,        // Serial input for shifting
    output [3:0] data_out   // 4-bit output (changed to wire)
);

    // Internal 4-bit register to hold the data
    reg [3:0] shift_reg;

    always @(posedge clk or posedge rst) begin
        if (rst) begin
            // Reset: Clear the shift register
            shift_reg <= 4'b0000;
        end else if (load) begin
            // Parallel load: Load data_in into the shift register
            shift_reg <= data_in;
        end else begin
            // Shift operation
            case (shift_dir)
                1'b0: begin
                    // Right shift
                    shift_reg <= {serial_in, shift_reg[3:1]};
                end
                1'b1: begin
                    // Left shift
                    shift_reg <= {shift_reg[2:0], serial_in};
                end
            endcase
        end
    end

    // Assign the output
    assign data_out = shift_reg;

endmodule

shift_reg_tb.v
`timescale 1ns / 1ps
`include "shift_reg.v"

module shift_reg_tb;

    // Inputs
    reg clk;
    reg rst;
    reg load;
    reg [3:0] data_in;
    reg shift_dir;
    reg serial_in;

    // Outputs
    wire [3:0] data_out;

    // Instantiate the shift_reg module
    shift_reg uut (
        .clk(clk),
        .rst(rst),
        .load(load),
        .data_in(data_in),
        .shift_dir(shift_dir),
        .serial_in(serial_in),
        .data_out(data_out)
    );

    // Clock generation
    always #5 clk = ~clk; // Toggle clock every 5 time units

    // VCD file dumping
    initial begin
        // Create a VCD file for waveform dumping
        $dumpfile("shift_reg_waveform.vcd"); // Name of the VCD file
        $dumpvars(0, shift_reg_tb); // Dump all signals in the testbench
    end

    // Testbench logic
    initial begin
        // Initialize inputs
        clk = 0;
        rst = 0;
        load = 0;
        data_in = 4'b0000;
        shift_dir = 0;
        serial_in = 0;

        //Reset the shift register
        rst = 1;
        #10;  
        rst = 0;
        #10;  

        //  Parallel load
        data_in = 4'b1101; // Load 1101
        load = 1;
        #10;  
        load = 0;
        #10;  

        // Right shift
        shift_dir = 0; // Set shift direction to right
        serial_in = 1; // Insert 1 into the leftmost bit
        #10;  
        serial_in = 0; // Insert 0 into the leftmost bit
        #10;  

        // Left shift
        shift_dir = 1; // Set shift direction to left
        serial_in = 1; // Insert 1 into the rightmost bit
        #10;  
        serial_in = 0; // Insert 0 into the rightmost bit
        #10;  

        // End simulation
        $stop;
    end

endmodule

shift_reg_waveform.vcd
$date
	Sat Jan 18 17:46:28 2025
$end
$version
	Icarus Verilog
$end
$timescale
	1ps
$end
$scope module shift_reg_tb $end
$var wire 4 ! data_out [3:0] $end
$var reg 1 " clk $end
$var reg 4 # data_in [3:0] $end
$var reg 1 $ load $end
$var reg 1 % rst $end
$var reg 1 & serial_in $end
$var reg 1 ' shift_dir $end
$scope module uut $end
$var wire 1 " clk $end
$var wire 4 ( data_in [3:0] $end
$var wire 4 ) data_out [3:0] $end
$var wire 1 $ load $end
$var wire 1 % rst $end
$var wire 1 & serial_in $end
$var wire 1 ' shift_dir $end
$var reg 4 * shift_reg [3:0] $end
$upscope $end
$upscope $end
$enddefinitions $end
$comment Show the parameter values. $end
$dumpall
$end
#0
$dumpvars
b0 *
b0 )
b0 (
0'
0&
1%
0$
b0 #
0"
b0 !
$end
#5000
1"
#10000
0"
0%
#15000
1"
#20000
0"
1$
b1101 #
b1101 (
#25000
b1101 !
b1101 )
b1101 *
1"
#30000
0"
0$
#35000
b110 !
b110 )
b110 *
1"
#40000
0"
1&
#45000
b1011 !
b1011 )
b1011 *
1"
#50000
0"
0&
#55000
b101 !
b101 )
b101 *
1"
#60000
0"
1&
1'
#65000
b1011 !
b1011 )
b1011 *
1"
#70000
0"
0&
#75000
b110 !
b110 )
b110 *
1"
